<SequencerGraph Name="Stage_2_3_Wave">

    <InitializePhase>
        <BlockPointExit Enable="True"/>
    </InitializePhase>

    <UpdatePhase>
        <WaitSecond Time="0.5"/>

        <TalkBalloon UniqueKey="Talk_0" SimpleTalkKey="Talk_Stage02_3_1"/>
        <WaitSecond Time="3.0"/>

        <SpawnCharacter CharacterKey="SukebanKatanaChan"  UniqueGroupKey="EnemyGroup" StartAIState="Entry_Battle" PositionUniqueKey="Player" Position="Random_-8^-5 Random_-5^5 0"            AllyInfo="Sukeban"/>
        <SpawnCharacter CharacterKey="SukebanKatanaChan"  UniqueGroupKey="EnemyGroup" StartAIState="Entry_Battle" PositionUniqueKey="Player" Position="Random_-8^-5 Random_-5^5 0"            AllyInfo="Sukeban"/>
        <SpawnCharacter CharacterKey="SukebanUziChan"     UniqueGroupKey="EnemyGroup" StartAIState="Entry_Battle" PositionUniqueKey="Player" Position="Random_-8^-5 Random_-5^5 0"            AllyInfo="Sukeban"/>
        <WaitSecond Time="5"/>
        <SpawnCharacter CharacterKey="SukebanKatanaChan"  UniqueGroupKey="EnemyGroup" StartAIState="Entry_Battle" PositionUniqueKey="Player" Position="Random_5^8 Random_-5^5 0"            AllyInfo="Sukeban"/>
        <SpawnCharacter CharacterKey="SukebanKatanaChan"  UniqueGroupKey="EnemyGroup" StartAIState="Entry_Battle" PositionUniqueKey="Player" Position="Random_5^8 Random_-5^5 0"            AllyInfo="Sukeban"/>
        <SpawnCharacter CharacterKey="SukebanUziChan"     UniqueGroupKey="EnemyGroup" StartAIState="Entry_Battle" PositionUniqueKey="Player" Position="Random_5^8 Random_-5^5 0"            AllyInfo="Sukeban"/>
        <WaitSecond Time="4"/>
        <SpawnCharacter CharacterKey="SukebanKatanaChan"  UniqueGroupKey="EnemyGroup" StartAIState="Entry_Battle" PositionUniqueKey="Player" Position="Random_-5^5 Random_5^8 0"             AllyInfo="Sukeban"/>
        <SpawnCharacter CharacterKey="SukebanUziChan"     UniqueGroupKey="EnemyGroup" StartAIState="Entry_Battle" PositionUniqueKey="Player" Position="Random_-5^5 Random_5^8 0"             AllyInfo="Sukeban"/>
        <WaitSecond Time="4"/>
        <SpawnCharacter CharacterKey="SukebanKatanaChan"  UniqueGroupKey="EnemyGroup" StartAIState="Entry_Battle" PositionUniqueKey="Player" Position="Random_-5^5 Random_-8^-5 0"           AllyInfo="Sukeban"/>
        <SpawnCharacter CharacterKey="SukebanUziChan"     UniqueGroupKey="EnemyGroup" StartAIState="Entry_Battle" PositionUniqueKey="Player" Position="Random_-5^5 Random_-8^-5 0"           AllyInfo="Sukeban"/>

        <WaitSecond Time="3.0"/>
        <SpawnCharacter CharacterKey="SukebanKatanaChan"  UniqueGroupKey="EnemyGroup" StartAIState="Entry_Battle" PositionUniqueKey="Player" Position="Random_-8^-5 Random_-5^5 0"            AllyInfo="Sukeban"/>
        <SpawnCharacter CharacterKey="SukebanKatanaChan"  UniqueGroupKey="EnemyGroup" StartAIState="Entry_Battle" PositionUniqueKey="Player" Position="Random_-8^-5 Random_-5^5 0"            AllyInfo="Sukeban"/>
        <SpawnCharacter CharacterKey="SukebanUziChan"     UniqueGroupKey="EnemyGroup" StartAIState="Entry_Battle" PositionUniqueKey="Player" Position="Random_-8^-5 Random_-5^5 0"            AllyInfo="Sukeban"/>
        <WaitSecond Time="4"/>
        <SpawnCharacter CharacterKey="SukebanKatanaChan"  UniqueGroupKey="EnemyGroup" StartAIState="Entry_Battle" PositionUniqueKey="Player" Position="Random_5^8 Random_-5^5 0"            AllyInfo="Sukeban"/>
        <SpawnCharacter CharacterKey="SukebanKatanaChan"  UniqueGroupKey="EnemyGroup" StartAIState="Entry_Battle" PositionUniqueKey="Player" Position="Random_5^8 Random_-5^5 0"            AllyInfo="Sukeban"/>
        <SpawnCharacter CharacterKey="SukebanUziChan"     UniqueGroupKey="EnemyGroup" StartAIState="Entry_Battle" PositionUniqueKey="Player" Position="Random_5^8 Random_-5^5 0"            AllyInfo="Sukeban"/>
        <WaitSecond Time="5"/>
        <SpawnCharacter CharacterKey="SukebanKatanaChan"  UniqueGroupKey="EnemyGroup" StartAIState="Entry_Battle" PositionUniqueKey="Player" Position="Random_-5^5 Random_5^8 0"             AllyInfo="Sukeban"/>
        <SpawnCharacter CharacterKey="SukebanUziChan"     UniqueGroupKey="EnemyGroup" StartAIState="Entry_Battle" PositionUniqueKey="Player" Position="Random_-5^5 Random_5^8 0"             AllyInfo="Sukeban"/>
        <WaitSecond Time="5"/>
        <SpawnCharacter CharacterKey="SukebanKatanaChan"  UniqueGroupKey="EnemyGroup" StartAIState="Entry_Battle" PositionUniqueKey="Player" Position="Random_-5^5 Random_-8^-5 0"           AllyInfo="Sukeban"/>
        <SpawnCharacter CharacterKey="SukebanUziChan"     UniqueGroupKey="EnemyGroup" StartAIState="Entry_Battle" PositionUniqueKey="Player" Position="Random_-5^5 Random_-8^-5 0"           AllyInfo="Sukeban"/>

        <WaitSecond Time="3.0"/>
        <SpawnCharacter CharacterKey="SukebanKatanaChan"  UniqueGroupKey="EnemyGroup" StartAIState="Entry_Battle" PositionUniqueKey="Player" Position="Random_-8^-5 Random_-5^5 0"            AllyInfo="Sukeban"/>
        <SpawnCharacter CharacterKey="SukebanKatanaChan"  UniqueGroupKey="EnemyGroup" StartAIState="Entry_Battle" PositionUniqueKey="Player" Position="Random_-8^-5 Random_-5^5 0"            AllyInfo="Sukeban"/>
        <SpawnCharacter CharacterKey="SukebanUziChan"     UniqueGroupKey="EnemyGroup" StartAIState="Entry_Battle" PositionUniqueKey="Player" Position="Random_-8^-5 Random_-5^5 0"            AllyInfo="Sukeban"/>
        <WaitSecond Time="3"/>
        <SpawnCharacter CharacterKey="SukebanKatanaChan"  UniqueGroupKey="EnemyGroup" StartAIState="Entry_Battle" PositionUniqueKey="Player" Position="Random_5^8 Random_-5^5 0"            AllyInfo="Sukeban"/>
        <SpawnCharacter CharacterKey="SukebanKatanaChan"  UniqueGroupKey="EnemyGroup" StartAIState="Entry_Battle" PositionUniqueKey="Player" Position="Random_5^8 Random_-5^5 0"            AllyInfo="Sukeban"/>
        <SpawnCharacter CharacterKey="SukebanUziChan"     UniqueGroupKey="EnemyGroup" StartAIState="Entry_Battle" PositionUniqueKey="Player" Position="Random_5^8 Random_-5^5 0"            AllyInfo="Sukeban"/>
        <WaitSecond Time="4"/>
        <SpawnCharacter CharacterKey="SukebanKatanaChan"  UniqueGroupKey="EnemyGroup" StartAIState="Entry_Battle" PositionUniqueKey="Player" Position="Random_-5^5 Random_5^8 0"             AllyInfo="Sukeban"/>
        <SpawnCharacter CharacterKey="SukebanUziChan"     UniqueGroupKey="EnemyGroup" StartAIState="Entry_Battle" PositionUniqueKey="Player" Position="Random_-5^5 Random_5^8 0"             AllyInfo="Sukeban"/>
        <WaitSecond Time="4"/>
        <SpawnCharacter CharacterKey="SukebanKatanaChan"  UniqueGroupKey="EnemyGroup" StartAIState="Entry_Battle" PositionUniqueKey="Player" Position="Random_-5^5 Random_-8^-5 0"           AllyInfo="Sukeban"/>
        <SpawnCharacter CharacterKey="SukebanUziChan"     UniqueGroupKey="EnemyGroup" StartAIState="Entry_Battle" PositionUniqueKey="Player" Position="Random_-5^5 Random_-8^-5 0"           AllyInfo="Sukeban"/>

        <DeadFence UniqueGroupKey="EnemyGroup"/>

        <WaitSecond Time="1.0"/>

        <TalkBalloon UniqueKey="Player" SimpleTalkKey="Talk_Stage02_3_2"/>
        <BlockPointExit Enable="False"/>

    </UpdatePhase>
    
</SequencerGraph>
