<AIPackage Name="AobaChoraisenPackage" DefaultState="AI_ChoraisenReady">

    <AIState>
        <AI_ChoraisenReady UpdateTime="0.0" TargetSearchType="Near" TargetSearchRange="999.0" SearchIdentifier="Player">
            <Event_OnExecute>
                <AIEvent Type="SetDirectionToTarget"/>
                <AIEvent Type="SetAction" Action="AC_ChoraisenReady"/>
            </Event_OnExecute>

            <Event_OnFrame>
                <AIEvent Type="SetDirectionToTarget"/>
            </Event_OnFrame>
            
            <Branch Condition="End" Execute="AI_ChoraisenPre"/>
        </AI_ChoraisenReady>

        <AI_ChoraisenPre UpdateTime="0.0" TargetSearchType="Near" TargetSearchRange="999.0" SearchIdentifier="Player">
            <Event_OnExecute>
                <AIEvent Type="SetAction" Action="AC_ChoraisenPre"/>
            </Event_OnExecute>

            <Branch Condition="End" Execute="AI_ChoraisenSlash"/>          
        </AI_ChoraisenPre>

        <AI_ChoraisenSlash UpdateTime="0.0" TargetSearchType="Near" TargetSearchRange="999.0" SearchIdentifier="Player">
            <Event_OnExecute>
                <AIEvent Type="SetAction" Action="AC_ChoraisenSlash"/>
            </Event_OnExecute>

            <Branch Condition="AttackSuccess" Execute="AI_ChoraisenSuccess"/>
            <Branch Condition="End" Execute="TerminatePackage"/>          
        </AI_ChoraisenSlash>

        <AI_ChoraisenSuccess UpdateTime="0.0" TargetSearchType="Near" TargetSearchRange="999.0" SearchIdentifier="Player">
            <Event_OnExecute>
                <AIEvent Type="SetAction" Action="AC_ChoraisenSuccess"/>
            </Event_OnExecute>

            <Branch Condition="End" Execute="TerminatePackage"/>    
        </AI_ChoraisenSuccess>

        <TerminatePackage>
            <Event_OnExecute>
                <AIEvent Type="TerminatePackage"/>
            </Event_OnExecute>
        </TerminatePackage>

    </AIState>

</AIPackage>